README.md
setup.py
mglib/__init__.py
mglib/exceptions.py
mglib/mime.py
mglib/path.py
mglib/pdfinfo.py
mglib/runcmd.py
mglib/shortcuts.py
mglib/stapler.py
mglib/step.py
mglib/storage.py
mglib/tiff.py
mglib/utils.py
mglib/wrapper.py
mglib.egg-info/PKG-INFO
mglib.egg-info/SOURCES.txt
mglib.egg-info/dependency_links.txt
mglib.egg-info/top_level.txt
mglib/conf/__init__.py
mglib/conf/default_settings.py
mglib/conf/settings.py
mglib/test/__init__.py
mglib/test/utils.py
test/test_mime.py
test/test_path.py
test/test_pdfinfo.py
test/test_settings.py
test/test_stapler.py
test/test_step.py
test/test_storage.py