Metadata-Version: 2.1
Name: mglib
Version: 1.3.1
Summary: Common code used across all Papermerge project utilities
Home-page: https://github.com/papermerge/mglib
Author: Eugen Ciur
Author-email: eugen@papermerge.com
License: Apache 2.0 License
Keywords: common,package,shared,papermerge,pdf,ocr,dms
Platform: UNKNOWN
Classifier: Programming Language :: Python :: 3
Classifier: License :: OSI Approved :: Apache Software License
Classifier: Operating System :: OS Independent
Requires-Python: >=3.7
